MANIFEST.in
README.rst
requirements.txt
setup.py
pandas_highcharts/__init__.py
pandas_highcharts/core.py
pandas_highcharts/display.py
pandas_highcharts/tests.py
pandas_highcharts.egg-info/PKG-INFO
pandas_highcharts.egg-info/SOURCES.txt
pandas_highcharts.egg-info/dependency_links.txt
pandas_highcharts.egg-info/requires.txt
pandas_highcharts.egg-info/top_level.txt